{
  "stats": {
    "submitted": 100,
    "finished": 100,
    "running": 0
  },
  "data": [
    {
      "config_id": 1,
      "instance": null,
      "seed": 42,
      "budget": null,
      "cost": 0.9445748829276606,
      "time": 0.0,
      "cpu_time": 0.0,
      "status": 1,
      "starttime": 0.0,
      "endtime": 0.0,
      "additional_info": {}
    },
    {
      "config_id": 1,
      "instance": null,
      "seed": 209652396,
      "budget": null,
      "cost": 0.9445748829276606,
      "time": 0.0,
      "cpu_time": 0.0,
      "status": 1,
      "starttime": 1752697434.4328861,
      "endtime": 1752697434.4341006,
      "additional_info": {}
    },
    {
      "config_id": 2,
      "instance": null,
      "seed": 42,
      "budget": null,
      "cost": 0.9902053513908514,
      "time": 0.0,
      "cpu_time": 0.0,
      "status": 1,
      "starttime": 1752697434.8638213,
      "endtime": 1752697434.8648217,
      "additional_info": {}
    },
    {
      "config_id": 2,
      "instance": null,
      "seed": 209652396,
      "budget": null,
      "cost": 0.9902053513908514,
      "time": 0.0,
      "cpu_time": 0.0,
      "status": 1,
      "starttime": 1752697434.8688855,
      "endtime": 1752697434.8698845,
      "additional_info": {}
    },
    {
      "config_id": 1,
      "instance": null,
      "seed": 398764591,
      "budget": null,
      "cost": 0.9445748829276606,
      "time": 0.0,
      "cpu_time": 0.0,
      "status": 1,
      "starttime": 1752697434.8738837,
      "endtime": 1752697434.874885,
      "additional_info": {}
    },
    {
      "config_id": 3,
      "instance": null,
      "seed": 42,
      "budget": null,
      "cost": 0.9578811148889729,
      "time": 0.0009984970092773438,
      "cpu_time": 0.0,
      "status": 1,
      "starttime": 1752697434.8791754,
      "endtime": 1752697434.8811746,
      "additional_info": {}
    },
    {
      "config_id": 3,
      "instance": null,
      "seed": 209652396,
      "budget": null,
      "cost": 0.9578811148889729,
      "time": 0.0,
      "cpu_time": 0.0,
      "status": 1,
      "starttime": 1752697434.8851724,
      "endtime": 1752697434.8861732,
      "additional_info": {}
    },
    {
      "config_id": 3,
      "instance": null,
      "seed": 398764591,
      "budget": null,
      "cost": 0.9578811148889729,
      "time": 0.0,
      "cpu_time": 0.0,
      "status": 1,
      "starttime": 1752697434.8891745,
      "endtime": 1752697434.890174,
      "additional_info": {}
    },
    {
      "config_id": 4,
      "instance": null,
      "seed": 42,
      "budget": null,
      "cost": 0.9446471802533881,
      "time": 0.0,
      "cpu_time": 0.0,
      "status": 1,
      "starttime": 1752697434.8951716,
      "endtime": 1752697434.896173,
      "additional_info": {}
    },
    {
      "config_id": 4,
      "instance": null,
      "seed": 209652396,
      "budget": null,
      "cost": 0.9446471802533881,
      "time": 0.0,
      "cpu_time": 0.0,
      "status": 1,
      "starttime": 1752697434.9001722,
      "endtime": 1752697434.9014084,
      "additional_info": {}
    },
    {
      "config_id": 4,
      "instance": null,
      "seed": 398764591,
      "budget": null,
      "cost": 0.9446471802533881,
      "time": 0.0,
      "cpu_time": 0.0,
      "status": 1,
      "starttime": 1752697434.9044087,
      "endtime": 1752697434.9054089,
      "additional_info": {}
    },
    {
      "config_id": 5,
      "instance": null,
      "seed": 42,
      "budget": null,
      "cost": 0.993978459660458,
      "time": 0.0009984970092773438,
      "cpu_time": 0.0,
      "status": 1,
      "starttime": 1752697434.909414,
      "endtime": 1752697434.9114125,
      "additional_info": {}
    },
    {
      "config_id": 5,
      "instance": null,
      "seed": 209652396,
      "budget": null,
      "cost": 0.993978459660458,
      "time": 0.0,
      "cpu_time": 0.0,
      "status": 1,
      "starttime": 1752697434.9154143,
      "endtime": 1752697434.9164126,
      "additional_info": {}
    },
    {
      "config_id": 5,
      "instance": null,
      "seed": 398764591,
      "budget": null,
      "cost": 0.993978459660458,
      "time": 0.0,
      "cpu_time": 0.0,
      "status": 1,
      "starttime": 1752697434.9209204,
      "endtime": 1752697434.9219258,
      "additional_info": {}
    },
    {
      "config_id": 6,
      "instance": null,
      "seed": 42,
      "budget": null,
      "cost": 0.9952487512500068,
      "time": 0.0,
      "cpu_time": 0.0,
      "status": 1,
      "starttime": 1752697434.9269273,
      "endtime": 1752697434.928927,
      "additional_info": {}
    },
    {
      "config_id": 6,
      "instance": null,
      "seed": 209652396,
      "budget": null,
      "cost": 0.9952487512500068,
      "time": 0.0,
      "cpu_time": 0.0,
      "status": 1,
      "starttime": 1752697434.9339263,
      "endtime": 1752697434.9349294,
      "additional_info": {}
    },
    {
      "config_id": 6,
      "instance": null,
      "seed": 398764591,
      "budget": null,
      "cost": 0.9952487512500068,
      "time": 0.0,
      "cpu_time": 0.0,
      "status": 1,
      "starttime": 1752697434.9389272,
      "endtime": 1752697434.9399266,
      "additional_info": {}
    },
    {
      "config_id": 7,
      "instance": null,
      "seed": 42,
      "budget": null,
      "cost": 0.9983292302159861,
      "time": 0.0,
      "cpu_time": 0.0,
      "status": 1,
      "starttime": 1752697434.9459262,
      "endtime": 1752697434.9469259,
      "additional_info": {}
    },
    {
      "config_id": 7,
      "instance": null,
      "seed": 209652396,
      "budget": null,
      "cost": 0.9983292302159861,
      "time": 0.0,
      "cpu_time": 0.0,
      "status": 1,
      "starttime": 1752697434.9519262,
      "endtime": 1752697434.9529257,
      "additional_info": {}
    },
    {
      "config_id": 7,
      "instance": null,
      "seed": 398764591,
      "budget": null,
      "cost": 0.9983292302159861,
      "time": 0.0,
      "cpu_time": 0.0,
      "status": 1,
      "starttime": 1752697434.9579265,
      "endtime": 1752697434.95893,
      "additional_info": {}
    },
    {
      "config_id": 8,
      "instance": null,
      "seed": 42,
      "budget": null,
      "cost": 0.9772944661948849,
      "time": 0.0,
      "cpu_time": 0.0,
      "status": 1,
      "starttime": 1752697434.963929,
      "endtime": 1752697434.964929,
      "additional_info": {}
    },
    {
      "config_id": 8,
      "instance": null,
      "seed": 209652396,
      "budget": null,
      "cost": 0.9772944661948849,
      "time": 0.0,
      "cpu_time": 0.0,
      "status": 1,
      "starttime": 1752697434.968929,
      "endtime": 1752697434.9699292,
      "additional_info": {}
    },
    {
      "config_id": 8,
      "instance": null,
      "seed": 398764591,
      "budget": null,
      "cost": 0.9772944661948849,
      "time": 0.0,
      "cpu_time": 0.0,
      "status": 1,
      "starttime": 1752697434.9749298,
      "endtime": 1752697434.975929,
      "additional_info": {}
    },
    {
      "config_id": 9,
      "instance": null,
      "seed": 42,
      "budget": null,
      "cost": 0.7808220980642635,
      "time": 0.0,
      "cpu_time": 0.0,
      "status": 1,
      "starttime": 1752697434.9809287,
      "endtime": 1752697434.9819293,
      "additional_info": {}
    },
    {
      "config_id": 9,
      "instance": null,
      "seed": 209652396,
      "budget": null,
      "cost": 0.7808220980642635,
      "time": 0.0,
      "cpu_time": 0.0,
      "status": 1,
      "starttime": 1752697434.986929,
      "endtime": 1752697434.9879289,
      "additional_info": {}
    },
    {
      "config_id": 9,
      "instance": null,
      "seed": 398764591,
      "budget": null,
      "cost": 0.7808220980642635,
      "time": 0.0,
      "cpu_time": 0.0,
      "status": 1,
      "starttime": 1752697434.992927,
      "endtime": 1752697434.9939256,
      "additional_info": {}
    },
    {
      "config_id": 10,
      "instance": null,
      "seed": 42,
      "budget": null,
      "cost": 0.9086767152935582,
      "time": 0.0,
      "cpu_time": 0.0,
      "status": 1,
      "starttime": 1752697435.4903297,
      "endtime": 1752697435.49133,
      "additional_info": {}
    },
    {
      "config_id": 10,
      "instance": null,
      "seed": 209652396,
      "budget": null,
      "cost": 0.9086767152935582,
      "time": 0.0,
      "cpu_time": 0.0,
      "status": 1,
      "starttime": 1752697435.4963315,
      "endtime": 1752697435.4973304,
      "additional_info": {}
    },
    {
      "config_id": 10,
      "instance": null,
      "seed": 398764591,
      "budget": null,
      "cost": 0.9086767152935582,
      "time": 0.0,
      "cpu_time": 0.0,
      "status": 1,
      "starttime": 1752697435.5013318,
      "endtime": 1752697435.5023308,
      "additional_info": {}
    },
    {
      "config_id": 11,
      "instance": null,
      "seed": 42,
      "budget": null,
      "cost": 0.976710548440125,
      "time": 0.0,
      "cpu_time": 0.0,
      "status": 1,
      "starttime": 1752697435.5083349,
      "endtime": 1752697435.5093348,
      "additional_info": {}
    },
    {
      "config_id": 11,
      "instance": null,
      "seed": 209652396,
      "budget": null,
      "cost": 0.976710548440125,
      "time": 0.0,
      "cpu_time": 0.0,
      "status": 1,
      "starttime": 1752697435.5135465,
      "endtime": 1752697435.5145457,
      "additional_info": {}
    },
    {
      "config_id": 11,
      "instance": null,
      "seed": 398764591,
      "budget": null,
      "cost": 0.976710548440125,
      "time": 0.0,
      "cpu_time": 0.0,
      "status": 1,
      "starttime": 1752697435.5195463,
      "endtime": 1752697435.5195463,
      "additional_info": {}
    },
    {
      "config_id": 12,
      "instance": null,
      "seed": 42,
      "budget": null,
      "cost": 0.6498368630368841,
      "time": 0.0,
      "cpu_time": 0.0,
      "status": 1,
      "starttime": 1752697435.5250568,
      "endtime": 1752697435.5263395,
      "additional_info": {}
    },
    {
      "config_id": 12,
      "instance": null,
      "seed": 209652396,
      "budget": null,
      "cost": 0.6498368630368841,
      "time": 0.0,
      "cpu_time": 0.0,
      "status": 1,
      "starttime": 1752697435.53134,
      "endtime": 1752697435.5326216,
      "additional_info": {}
    },
    {
      "config_id": 12,
      "instance": null,
      "seed": 398764591,
      "budget": null,
      "cost": 0.6498368630368841,
      "time": 0.0,
      "cpu_time": 0.0,
      "status": 1,
      "starttime": 1752697435.5378706,
      "endtime": 1752697435.5388696,
      "additional_info": {}
    },
    {
      "config_id": 13,
      "instance": null,
      "seed": 42,
      "budget": null,
      "cost": 0.94749263364069,
      "time": 0.0,
      "cpu_time": 0.0,
      "status": 1,
      "starttime": 1752697435.5458713,
      "endtime": 1752697435.5468676,
      "additional_info": {}
    },
    {
      "config_id": 13,
      "instance": null,
      "seed": 209652396,
      "budget": null,
      "cost": 0.94749263364069,
      "time": 0.0,
      "cpu_time": 0.0,
      "status": 1,
      "starttime": 1752697435.5518699,
      "endtime": 1752697435.5531244,
      "additional_info": {}
    },
    {
      "config_id": 13,
      "instance": null,
      "seed": 398764591,
      "budget": null,
      "cost": 0.94749263364069,
      "time": 0.0,
      "cpu_time": 0.0,
      "status": 1,
      "starttime": 1752697435.5582287,
      "endtime": 1752697435.5592277,
      "additional_info": {}
    },
    {
      "config_id": 14,
      "instance": null,
      "seed": 42,
      "budget": null,
      "cost": 0.9338991842457197,
      "time": 0.0009996891021728516,
      "cpu_time": 0.0,
      "status": 1,
      "starttime": 1752697435.56631,
      "endtime": 1752697435.5673096,
      "additional_info": {}
    },
    {
      "config_id": 14,
      "instance": null,
      "seed": 209652396,
      "budget": null,
      "cost": 0.9338991842457197,
      "time": 0.0,
      "cpu_time": 0.0,
      "status": 1,
      "starttime": 1752697435.5723102,
      "endtime": 1752697435.5733094,
      "additional_info": {}
    },
    {
      "config_id": 14,
      "instance": null,
      "seed": 398764591,
      "budget": null,
      "cost": 0.9338991842457197,
      "time": 0.0,
      "cpu_time": 0.0,
      "status": 1,
      "starttime": 1752697435.5793083,
      "endtime": 1752697435.5803084,
      "additional_info": {}
    },
    {
      "config_id": 15,
      "instance": null,
      "seed": 42,
      "budget": null,
      "cost": 0.9995975086138889,
      "time": 0.0,
      "cpu_time": 0.0,
      "status": 1,
      "starttime": 1752697435.5883105,
      "endtime": 1752697435.5893106,
      "additional_info": {}
    },
    {
      "config_id": 15,
      "instance": null,
      "seed": 209652396,
      "budget": null,
      "cost": 0.9995975086138889,
      "time": 0.0,
      "cpu_time": 0.0,
      "status": 1,
      "starttime": 1752697435.595311,
      "endtime": 1752697435.5963104,
      "additional_info": {}
    },
    {
      "config_id": 15,
      "instance": null,
      "seed": 398764591,
      "budget": null,
      "cost": 0.9995975086138889,
      "time": 0.0,
      "cpu_time": 0.0,
      "status": 1,
      "starttime": 1752697435.6023092,
      "endtime": 1752697435.6033108,
      "additional_info": {}
    },
    {
      "config_id": 16,
      "instance": null,
      "seed": 42,
      "budget": null,
      "cost": 0.975496200706784,
      "time": 0.0,
      "cpu_time": 0.0,
      "status": 1,
      "starttime": 1752697435.6113153,
      "endtime": 1752697435.612315,
      "additional_info": {}
    },
    {
      "config_id": 16,
      "instance": null,
      "seed": 209652396,
      "budget": null,
      "cost": 0.975496200706784,
      "time": 0.0,
      "cpu_time": 0.0,
      "status": 1,
      "starttime": 1752697435.6193166,
      "endtime": 1752697435.6203148,
      "additional_info": {}
    },
    {
      "config_id": 16,
      "instance": null,
      "seed": 398764591,
      "budget": null,
      "cost": 0.975496200706784,
      "time": 0.0,
      "cpu_time": 0.0,
      "status": 1,
      "starttime": 1752697435.6268246,
      "endtime": 1752697435.6278238,
      "additional_info": {}
    },
    {
      "config_id": 17,
      "instance": null,
      "seed": 42,
      "budget": null,
      "cost": 0.9600920472397555,
      "time": 0.0,
      "cpu_time": 0.0,
      "status": 1,
      "starttime": 1752697435.635824,
      "endtime": 1752697435.6368232,
      "additional_info": {}
    },
    {
      "config_id": 17,
      "instance": null,
      "seed": 209652396,
      "budget": null,
      "cost": 0.9600920472397555,
      "time": 0.0,
      "cpu_time": 0.0,
      "status": 1,
      "starttime": 1752697435.6440108,
      "endtime": 1752697435.6450102,
      "additional_info": {}
    },
    {
      "config_id": 17,
      "instance": null,
      "seed": 398764591,
      "budget": null,
      "cost": 0.9600920472397555,
      "time": 0.0,
      "cpu_time": 0.0,
      "status": 1,
      "starttime": 1752697435.6510103,
      "endtime": 1752697435.6520104,
      "additional_info": {}
    },
    {
      "config_id": 18,
      "instance": null,
      "seed": 42,
      "budget": null,
      "cost": 0.9047182015111879,
      "time": 0.0,
      "cpu_time": 0.0,
      "status": 1,
      "starttime": 1752697436.2002044,
      "endtime": 1752697436.2012038,
      "additional_info": {}
    },
    {
      "config_id": 18,
      "instance": null,
      "seed": 209652396,
      "budget": null,
      "cost": 0.9047182015111879,
      "time": 0.0,
      "cpu_time": 0.0,
      "status": 1,
      "starttime": 1752697436.2092073,
      "endtime": 1752697436.2102067,
      "additional_info": {}
    },
    {
      "config_id": 18,
      "instance": null,
      "seed": 398764591,
      "budget": null,
      "cost": 0.9047182015111879,
      "time": 0.0,
      "cpu_time": 0.0,
      "status": 1,
      "starttime": 1752697436.2162073,
      "endtime": 1752697436.217206,
      "additional_info": {}
    },
    {
      "config_id": 19,
      "instance": null,
      "seed": 42,
      "budget": null,
      "cost": 0.18205708385546737,
      "time": 0.0,
      "cpu_time": 0.0,
      "status": 1,
      "starttime": 1752697436.2247148,
      "endtime": 1752697436.2257166,
      "additional_info": {}
    },
    {
      "config_id": 19,
      "instance": null,
      "seed": 209652396,
      "budget": null,
      "cost": 0.18205708385546737,
      "time": 0.0,
      "cpu_time": 0.0,
      "status": 1,
      "starttime": 1752697436.2317157,
      "endtime": 1752697436.232715,
      "additional_info": {}
    },
    {
      "config_id": 19,
      "instance": null,
      "seed": 398764591,
      "budget": null,
      "cost": 0.18205708385546737,
      "time": 0.0,
      "cpu_time": 0.0,
      "status": 1,
      "starttime": 1752697436.239714,
      "endtime": 1752697436.2407122,
      "additional_info": {}
    },
    {
      "config_id": 20,
      "instance": null,
      "seed": 42,
      "budget": null,
      "cost": 0.7605065703480052,
      "time": 0.0,
      "cpu_time": 0.0,
      "status": 1,
      "starttime": 1752697436.2511396,
      "endtime": 1752697436.2521396,
      "additional_info": {}
    },
    {
      "config_id": 20,
      "instance": null,
      "seed": 209652396,
      "budget": null,
      "cost": 0.7605065703480052,
      "time": 0.0,
      "cpu_time": 0.0,
      "status": 1,
      "starttime": 1752697436.260141,
      "endtime": 1752697436.2611394,
      "additional_info": {}
    },
    {
      "config_id": 20,
      "instance": null,
      "seed": 398764591,
      "budget": null,
      "cost": 0.7605065703480052,
      "time": 0.0,
      "cpu_time": 0.0,
      "status": 1,
      "starttime": 1752697436.2685285,
      "endtime": 1752697436.2695284,
      "additional_info": {}
    },
    {
      "config_id": 21,
      "instance": null,
      "seed": 42,
      "budget": null,
      "cost": 0.9772640152141139,
      "time": 0.0,
      "cpu_time": 0.0,
      "status": 1,
      "starttime": 1752697436.2785275,
      "endtime": 1752697436.2795286,
      "additional_info": {}
    },
    {
      "config_id": 21,
      "instance": null,
      "seed": 209652396,
      "budget": null,
      "cost": 0.9772640152141139,
      "time": 0.0,
      "cpu_time": 0.0,
      "status": 1,
      "starttime": 1752697436.2855287,
      "endtime": 1752697436.2865288,
      "additional_info": {}
    },
    {
      "config_id": 21,
      "instance": null,
      "seed": 398764591,
      "budget": null,
      "cost": 0.9772640152141139,
      "time": 0.0,
      "cpu_time": 0.0,
      "status": 1,
      "starttime": 1752697436.2935288,
      "endtime": 1752697436.2945285,
      "additional_info": {}
    },
    {
      "config_id": 22,
      "instance": null,
      "seed": 42,
      "budget": null,
      "cost": 0.9998843787290707,
      "time": 0.0,
      "cpu_time": 0.0,
      "status": 1,
      "starttime": 1752697436.302527,
      "endtime": 1752697436.3035269,
      "additional_info": {}
    },
    {
      "config_id": 22,
      "instance": null,
      "seed": 209652396,
      "budget": null,
      "cost": 0.9998843787290707,
      "time": 0.0,
      "cpu_time": 0.0,
      "status": 1,
      "starttime": 1752697436.3105364,
      "endtime": 1752697436.3115351,
      "additional_info": {}
    },
    {
      "config_id": 22,
      "instance": null,
      "seed": 398764591,
      "budget": null,
      "cost": 0.9998843787290707,
      "time": 0.0,
      "cpu_time": 0.0,
      "status": 1,
      "starttime": 1752697436.3185356,
      "endtime": 1752697436.319536,
      "additional_info": {}
    },
    {
      "config_id": 23,
      "instance": null,
      "seed": 42,
      "budget": null,
      "cost": 0.7860455471819511,
      "time": 0.0,
      "cpu_time": 0.0,
      "status": 1,
      "starttime": 1752697436.3280504,
      "endtime": 1752697436.3290508,
      "additional_info": {}
    },
    {
      "config_id": 23,
      "instance": null,
      "seed": 209652396,
      "budget": null,
      "cost": 0.7860455471819511,
      "time": 0.0,
      "cpu_time": 0.0,
      "status": 1,
      "starttime": 1752697436.3360505,
      "endtime": 1752697436.337051,
      "additional_info": {}
    },
    {
      "config_id": 23,
      "instance": null,
      "seed": 398764591,
      "budget": null,
      "cost": 0.7860455471819511,
      "time": 0.0,
      "cpu_time": 0.0,
      "status": 1,
      "starttime": 1752697436.3440495,
      "endtime": 1752697436.3450477,
      "additional_info": {}
    },
    {
      "config_id": 24,
      "instance": null,
      "seed": 42,
      "budget": null,
      "cost": 0.9703462350430698,
      "time": 0.0,
      "cpu_time": 0.0,
      "status": 1,
      "starttime": 1752697436.355051,
      "endtime": 1752697436.356051,
      "additional_info": {}
    },
    {
      "config_id": 24,
      "instance": null,
      "seed": 209652396,
      "budget": null,
      "cost": 0.9703462350430698,
      "time": 0.0,
      "cpu_time": 0.0,
      "status": 1,
      "starttime": 1752697436.3630512,
      "endtime": 1752697436.3640509,
      "additional_info": {}
    },
    {
      "config_id": 24,
      "instance": null,
      "seed": 398764591,
      "budget": null,
      "cost": 0.9703462350430698,
      "time": 0.0,
      "cpu_time": 0.0,
      "status": 1,
      "starttime": 1752697436.3710518,
      "endtime": 1752697436.3720512,
      "additional_info": {}
    },
    {
      "config_id": 25,
      "instance": null,
      "seed": 42,
      "budget": null,
      "cost": 0.8048534695998524,
      "time": 0.0,
      "cpu_time": 0.0,
      "status": 1,
      "starttime": 1752697436.381051,
      "endtime": 1752697436.3820498,
      "additional_info": {}
    },
    {
      "config_id": 25,
      "instance": null,
      "seed": 209652396,
      "budget": null,
      "cost": 0.8048534695998524,
      "time": 0.0,
      "cpu_time": 0.0,
      "status": 1,
      "starttime": 1752697436.3900495,
      "endtime": 1752697436.3910491,
      "additional_info": {}
    },
    {
      "config_id": 25,
      "instance": null,
      "seed": 398764591,
      "budget": null,
      "cost": 0.8048534695998524,
      "time": 0.0,
      "cpu_time": 0.0,
      "status": 1,
      "starttime": 1752697436.4000506,
      "endtime": 1752697436.40105,
      "additional_info": {}
    },
    {
      "config_id": 26,
      "instance": null,
      "seed": 42,
      "budget": null,
      "cost": 0.885476277267359,
      "time": 0.0,
      "cpu_time": 0.0,
      "status": 1,
      "starttime": 1752697436.9060988,
      "endtime": 1752697436.9071028,
      "additional_info": {}
    },
    {
      "config_id": 26,
      "instance": null,
      "seed": 209652396,
      "budget": null,
      "cost": 0.885476277267359,
      "time": 0.0,
      "cpu_time": 0.0,
      "status": 1,
      "starttime": 1752697436.9161065,
      "endtime": 1752697436.9171062,
      "additional_info": {}
    },
    {
      "config_id": 26,
      "instance": null,
      "seed": 398764591,
      "budget": null,
      "cost": 0.885476277267359,
      "time": 0.0,
      "cpu_time": 0.0,
      "status": 1,
      "starttime": 1752697436.9256213,
      "endtime": 1752697436.9266207,
      "additional_info": {}
    },
    {
      "config_id": 27,
      "instance": null,
      "seed": 42,
      "budget": null,
      "cost": 0.27638260128078723,
      "time": 0.0,
      "cpu_time": 0.0,
      "status": 1,
      "starttime": 1752697436.9356177,
      "endtime": 1752697436.9366186,
      "additional_info": {}
    },
    {
      "config_id": 27,
      "instance": null,
      "seed": 209652396,
      "budget": null,
      "cost": 0.27638260128078723,
      "time": 0.0,
      "cpu_time": 0.0,
      "status": 1,
      "starttime": 1752697436.9446187,
      "endtime": 1752697436.9456174,
      "additional_info": {}
    },
    {
      "config_id": 27,
      "instance": null,
      "seed": 398764591,
      "budget": null,
      "cost": 0.27638260128078723,
      "time": 0.0,
      "cpu_time": 0.0,
      "status": 1,
      "starttime": 1752697436.9536185,
      "endtime": 1752697436.9546173,
      "additional_info": {}
    },
    {
      "config_id": 28,
      "instance": null,
      "seed": 42,
      "budget": null,
      "cost": 0.9917798193728141,
      "time": 0.0,
      "cpu_time": 0.0,
      "status": 1,
      "starttime": 1752697436.9650984,
      "endtime": 1752697436.966098,
      "additional_info": {}
    },
    {
      "config_id": 28,
      "instance": null,
      "seed": 209652396,
      "budget": null,
      "cost": 0.9917798193728141,
      "time": 0.0,
      "cpu_time": 0.0,
      "status": 1,
      "starttime": 1752697436.9741547,
      "endtime": 1752697436.975154,
      "additional_info": {}
    },
    {
      "config_id": 28,
      "instance": null,
      "seed": 398764591,
      "budget": null,
      "cost": 0.9917798193728141,
      "time": 0.0,
      "cpu_time": 0.0,
      "status": 1,
      "starttime": 1752697436.983157,
      "endtime": 1752697436.9841568,
      "additional_info": {}
    },
    {
      "config_id": 29,
      "instance": null,
      "seed": 42,
      "budget": null,
      "cost": 0.9808878228484014,
      "time": 0.0,
      "cpu_time": 0.0,
      "status": 1,
      "starttime": 1752697436.9941573,
      "endtime": 1752697436.995156,
      "additional_info": {}
    },
    {
      "config_id": 29,
      "instance": null,
      "seed": 209652396,
      "budget": null,
      "cost": 0.9808878228484014,
      "time": 0.0,
      "cpu_time": 0.0,
      "status": 1,
      "starttime": 1752697437.0031579,
      "endtime": 1752697437.0041564,
      "additional_info": {}
    },
    {
      "config_id": 29,
      "instance": null,
      "seed": 398764591,
      "budget": null,
      "cost": 0.9808878228484014,
      "time": 0.0,
      "cpu_time": 0.0,
      "status": 1,
      "starttime": 1752697437.0131655,
      "endtime": 1752697437.0151641,
      "additional_info": {}
    },
    {
      "config_id": 30,
      "instance": null,
      "seed": 42,
      "budget": null,
      "cost": 0.999861147535383,
      "time": 0.0,
      "cpu_time": 0.0,
      "status": 1,
      "starttime": 1752697437.024678,
      "endtime": 1752697437.0256782,
      "additional_info": {}
    },
    {
      "config_id": 30,
      "instance": null,
      "seed": 209652396,
      "budget": null,
      "cost": 0.999861147535383,
      "time": 0.0,
      "cpu_time": 0.0,
      "status": 1,
      "starttime": 1752697437.0336792,
      "endtime": 1752697437.0346787,
      "additional_info": {}
    },
    {
      "config_id": 30,
      "instance": null,
      "seed": 398764591,
      "budget": null,
      "cost": 0.999861147535383,
      "time": 0.0,
      "cpu_time": 0.0,
      "status": 1,
      "starttime": 1752697437.0426774,
      "endtime": 1752697437.0436788,
      "additional_info": {}
    },
    {
      "config_id": 31,
      "instance": null,
      "seed": 42,
      "budget": null,
      "cost": 0.9998045056525546,
      "time": 0.0,
      "cpu_time": 0.0,
      "status": 1,
      "starttime": 1752697437.0536788,
      "endtime": 1752697437.0546794,
      "additional_info": {}
    },
    {
      "config_id": 31,
      "instance": null,
      "seed": 209652396,
      "budget": null,
      "cost": 0.9998045056525546,
      "time": 0.0,
      "cpu_time": 0.0,
      "status": 1,
      "starttime": 1752697437.0636764,
      "endtime": 1752697437.0646756,
      "additional_info": {}
    },
    {
      "config_id": 31,
      "instance": null,
      "seed": 398764591,
      "budget": null,
      "cost": 0.9998045056525546,
      "time": 0.0,
      "cpu_time": 0.0,
      "status": 1,
      "starttime": 1752697437.0726793,
      "endtime": 1752697437.0736785,
      "additional_info": {}
    },
    {
      "config_id": 32,
      "instance": null,
      "seed": 42,
      "budget": null,
      "cost": 0.9961678525120986,
      "time": 0.0,
      "cpu_time": 0.0,
      "status": 1,
      "starttime": 1752697437.0836782,
      "endtime": 1752697437.0846777,
      "additional_info": {}
    },
    {
      "config_id": 32,
      "instance": null,
      "seed": 209652396,
      "budget": null,
      "cost": 0.9961678525120986,
      "time": 0.0,
      "cpu_time": 0.0,
      "status": 1,
      "starttime": 1752697437.0966787,
      "endtime": 1752697437.0976775,
      "additional_info": {}
    },
    {
      "config_id": 32,
      "instance": null,
      "seed": 398764591,
      "budget": null,
      "cost": 0.9961678525120986,
      "time": 0.0,
      "cpu_time": 0.0,
      "status": 1,
      "starttime": 1752697437.1056783,
      "endtime": 1752697437.1066782,
      "additional_info": {}
    },
    {
      "config_id": 33,
      "instance": null,
      "seed": 42,
      "budget": null,
      "cost": 0.9963797946633577,
      "time": 0.0,
      "cpu_time": 0.0,
      "status": 1,
      "starttime": 1752697437.1176856,
      "endtime": 1752697437.1186845,
      "additional_info": {}
    },
    {
      "config_id": 33,
      "instance": null,
      "seed": 209652396,
      "budget": null,
      "cost": 0.9963797946633577,
      "time": 0.0,
      "cpu_time": 0.0,
      "status": 1,
      "starttime": 1752697437.1271968,
      "endtime": 1752697437.1281972,
      "additional_info": {}
    },
    {
      "config_id": 33,
      "instance": null,
      "seed": 398764591,
      "budget": null,
      "cost": 0.9963797946633577,
      "time": 0.0,
      "cpu_time": 0.0,
      "status": 1,
      "starttime": 1752697437.1371977,
      "endtime": 1752697437.1381962,
      "additional_info": {}
    },
    {
      "config_id": 34,
      "instance": null,
      "seed": 42,
      "budget": null,
      "cost": 0.9737098479012979,
      "time": 0.0,
      "cpu_time": 0.0,
      "status": 1,
      "starttime": 1752697437.1611936,
      "endtime": 1752697437.1631937,
      "additional_info": {}
    },
    {
      "config_id": 34,
      "instance": null,
      "seed": 209652396,
      "budget": null,
      "cost": 0.9737098479012979,
      "time": 0.0,
      "cpu_time": 0.0,
      "status": 1,
      "starttime": 1752697437.1731951,
      "endtime": 1752697437.174194,
      "additional_info": {}
    }
  ],
  "configs": {
    "1": {
      "x": 10106
    },
    "2": {
      "x": 2859
    },
    "3": {
      "x": 797
    },
    "4": {
      "x": 1554
    },
    "5": {
      "x": 487
    },
    "6": {
      "x": 1769
    },
    "7": {
      "x": 109
    },
    "8": {
      "x": 214
    },
    "9": {
      "x": 289
    },
    "10": {
      "x": 291
    },
    "11": {
      "x": 285
    },
    "12": {
      "x": 284
    },
    "13": {
      "x": 299
    },
    "14": {
      "x": 294
    },
    "15": {
      "x": 15443
    },
    "16": {
      "x": 3836
    },
    "17": {
      "x": 2207
    },
    "18": {
      "x": 279
    },
    "19": {
      "x": 283
    },
    "20": {
      "x": 281
    },
    "21": {
      "x": 11239
    },
    "22": {
      "x": 15447
    },
    "23": {
      "x": 278
    },
    "24": {
      "x": 280
    },
    "25": {
      "x": 277
    },
    "26": {
      "x": 756
    },
    "27": {
      "x": 282
    },
    "28": {
      "x": 14879
    },
    "29": {
      "x": 14126
    },
    "30": {
      "x": 240
    },
    "31": {
      "x": 235
    },
    "32": {
      "x": 238
    },
    "33": {
      "x": 237
    },
    "34": {
      "x": 7943
    }
  },
  "config_origins": {
    "1": "Initial design",
    "2": "Acquisition Function Maximizer: Local Search",
    "3": "Acquisition Function Maximizer: Local Search",
    "4": "Acquisition Function Maximizer: Local Search",
    "5": "Acquisition Function Maximizer: Local Search",
    "6": "Acquisition Function Maximizer: Local Search",
    "7": "Acquisition Function Maximizer: Local Search",
    "8": "Acquisition Function Maximizer: Local Search",
    "9": "Acquisition Function Maximizer: Local Search",
    "10": "Acquisition Function Maximizer: Local Search",
    "11": "Acquisition Function Maximizer: Local Search",
    "12": "Acquisition Function Maximizer: Local Search",
    "13": "Acquisition Function Maximizer: Local Search",
    "14": "Acquisition Function Maximizer: Local Search",
    "15": "Random Search",
    "16": "Random Search",
    "17": "Random Search",
    "18": "Acquisition Function Maximizer: Local Search",
    "19": "Acquisition Function Maximizer: Local Search",
    "20": "Acquisition Function Maximizer: Local Search",
    "21": "Random Search",
    "22": "Random Search",
    "23": "Acquisition Function Maximizer: Local Search",
    "24": "Acquisition Function Maximizer: Local Search",
    "25": "Acquisition Function Maximizer: Local Search",
    "26": "Random Search",
    "27": "Acquisition Function Maximizer: Local Search",
    "28": "Random Search",
    "29": "Random Search",
    "30": "Acquisition Function Maximizer: Local Search",
    "31": "Acquisition Function Maximizer: Local Search",
    "32": "Acquisition Function Maximizer: Local Search",
    "33": "Acquisition Function Maximizer: Local Search",
    "34": "Random Search"
  }
}