{
  "stats": {
    "submitted": 96,
    "finished": 96,
    "running": 0
  },
  "data": [
    {
      "config_id": 1,
      "instance": null,
      "seed": 42,
      "budget": null,
      "cost": 0.8685,
      "time": 0.0,
      "cpu_time": 0.0,
      "status": 1,
      "starttime": 0.0,
      "endtime": 0.0,
      "additional_info": {}
    },
    {
      "config_id": 1,
      "instance": null,
      "seed": 209652396,
      "budget": null,
      "cost": 0.8685,
      "time": 0.0,
      "cpu_time": 0.0,
      "status": 1,
      "starttime": 1758767662.260935,
      "endtime": 1758767662.261935,
      "additional_info": {}
    },
    {
      "config_id": 2,
      "instance": null,
      "seed": 42,
      "budget": null,
      "cost": 0.9966,
      "time": 0.0,
      "cpu_time": 0.0,
      "status": 1,
      "starttime": 1758767662.6809354,
      "endtime": 1758767662.6819353,
      "additional_info": {}
    },
    {
      "config_id": 2,
      "instance": null,
      "seed": 209652396,
      "budget": null,
      "cost": 0.9966,
      "time": 0.0,
      "cpu_time": 0.0,
      "status": 1,
      "starttime": 1758767662.6849349,
      "endtime": 1758767662.6859348,
      "additional_info": {}
    },
    {
      "config_id": 1,
      "instance": null,
      "seed": 398764591,
      "budget": null,
      "cost": 0.8685,
      "time": 0.0,
      "cpu_time": 0.0,
      "status": 1,
      "starttime": 1758767662.6909351,
      "endtime": 1758767662.6909351,
      "additional_info": {}
    },
    {
      "config_id": 3,
      "instance": null,
      "seed": 42,
      "budget": null,
      "cost": 0.9893,
      "time": 0.0,
      "cpu_time": 0.0,
      "status": 1,
      "starttime": 1758767662.695935,
      "endtime": 1758767662.696936,
      "additional_info": {}
    },
    {
      "config_id": 3,
      "instance": null,
      "seed": 209652396,
      "budget": null,
      "cost": 0.9893,
      "time": 0.0,
      "cpu_time": 0.0,
      "status": 1,
      "starttime": 1758767662.699935,
      "endtime": 1758767662.700935,
      "additional_info": {}
    },
    {
      "config_id": 3,
      "instance": null,
      "seed": 398764591,
      "budget": null,
      "cost": 0.9893,
      "time": 0.0,
      "cpu_time": 0.0,
      "status": 1,
      "starttime": 1758767662.7049348,
      "endtime": 1758767662.7059348,
      "additional_info": {}
    },
    {
      "config_id": 4,
      "instance": null,
      "seed": 42,
      "budget": null,
      "cost": 0.9372,
      "time": 0.0,
      "cpu_time": 0.0,
      "status": 1,
      "starttime": 1758767662.7109349,
      "endtime": 1758767662.7109349,
      "additional_info": {}
    },
    {
      "config_id": 4,
      "instance": null,
      "seed": 209652396,
      "budget": null,
      "cost": 0.9372,
      "time": 0.0,
      "cpu_time": 0.0,
      "status": 1,
      "starttime": 1758767662.7149348,
      "endtime": 1758767662.7159348,
      "additional_info": {}
    },
    {
      "config_id": 4,
      "instance": null,
      "seed": 398764591,
      "budget": null,
      "cost": 0.9372,
      "time": 0.0,
      "cpu_time": 0.0,
      "status": 1,
      "starttime": 1758767662.719935,
      "endtime": 1758767662.719935,
      "additional_info": {}
    },
    {
      "config_id": 5,
      "instance": null,
      "seed": 42,
      "budget": null,
      "cost": 0.9905,
      "time": 0.0,
      "cpu_time": 0.0,
      "status": 1,
      "starttime": 1758767662.7249348,
      "endtime": 1758767662.7249348,
      "additional_info": {}
    },
    {
      "config_id": 5,
      "instance": null,
      "seed": 209652396,
      "budget": null,
      "cost": 0.9905,
      "time": 0.0,
      "cpu_time": 0.0,
      "status": 1,
      "starttime": 1758767662.7289352,
      "endtime": 1758767662.729935,
      "additional_info": {}
    },
    {
      "config_id": 5,
      "instance": null,
      "seed": 398764591,
      "budget": null,
      "cost": 0.9905,
      "time": 0.0,
      "cpu_time": 0.0,
      "status": 1,
      "starttime": 1758767662.7359352,
      "endtime": 1758767662.7359352,
      "additional_info": {}
    },
    {
      "config_id": 6,
      "instance": null,
      "seed": 42,
      "budget": null,
      "cost": 1.0,
      "time": 0.0009992122650146484,
      "cpu_time": 0.0,
      "status": 1,
      "starttime": 1758767662.7439356,
      "endtime": 1758767662.7449348,
      "additional_info": {}
    },
    {
      "config_id": 6,
      "instance": null,
      "seed": 209652396,
      "budget": null,
      "cost": 1.0,
      "time": 0.0,
      "cpu_time": 0.0,
      "status": 1,
      "starttime": 1758767662.747935,
      "endtime": 1758767662.748935,
      "additional_info": {}
    },
    {
      "config_id": 6,
      "instance": null,
      "seed": 398764591,
      "budget": null,
      "cost": 1.0,
      "time": 0.0,
      "cpu_time": 0.0,
      "status": 1,
      "starttime": 1758767662.752935,
      "endtime": 1758767662.7539349,
      "additional_info": {}
    },
    {
      "config_id": 7,
      "instance": null,
      "seed": 42,
      "budget": null,
      "cost": 0.9979,
      "time": 0.0,
      "cpu_time": 0.0,
      "status": 1,
      "starttime": 1758767662.7579348,
      "endtime": 1758767662.758935,
      "additional_info": {}
    },
    {
      "config_id": 7,
      "instance": null,
      "seed": 209652396,
      "budget": null,
      "cost": 0.9979,
      "time": 0.0,
      "cpu_time": 0.0,
      "status": 1,
      "starttime": 1758767662.7629347,
      "endtime": 1758767662.763935,
      "additional_info": {}
    },
    {
      "config_id": 7,
      "instance": null,
      "seed": 398764591,
      "budget": null,
      "cost": 0.9979,
      "time": 0.0,
      "cpu_time": 0.0,
      "status": 1,
      "starttime": 1758767662.768935,
      "endtime": 1758767662.768935,
      "additional_info": {}
    },
    {
      "config_id": 8,
      "instance": null,
      "seed": 42,
      "budget": null,
      "cost": 0.0,
      "time": 0.0,
      "cpu_time": 0.0,
      "status": 1,
      "starttime": 1758767662.773935,
      "endtime": 1758767662.773935,
      "additional_info": {}
    },
    {
      "config_id": 8,
      "instance": null,
      "seed": 209652396,
      "budget": null,
      "cost": 0.0,
      "time": 0.0,
      "cpu_time": 0.0,
      "status": 1,
      "starttime": 1758767662.777935,
      "endtime": 1758767662.778935,
      "additional_info": {}
    },
    {
      "config_id": 8,
      "instance": null,
      "seed": 398764591,
      "budget": null,
      "cost": 0.0,
      "time": 0.0,
      "cpu_time": 0.0,
      "status": 1,
      "starttime": 1758767662.786935,
      "endtime": 1758767662.7879355,
      "additional_info": {}
    },
    {
      "config_id": 9,
      "instance": null,
      "seed": 42,
      "budget": null,
      "cost": 0.9883,
      "time": 0.0,
      "cpu_time": 0.0,
      "status": 1,
      "starttime": 1758767662.7949352,
      "endtime": 1758767662.7949352,
      "additional_info": {}
    },
    {
      "config_id": 9,
      "instance": null,
      "seed": 209652396,
      "budget": null,
      "cost": 0.9883,
      "time": 0.0,
      "cpu_time": 0.0,
      "status": 1,
      "starttime": 1758767662.7999346,
      "endtime": 1758767662.800935,
      "additional_info": {}
    },
    {
      "config_id": 9,
      "instance": null,
      "seed": 398764591,
      "budget": null,
      "cost": 0.9883,
      "time": 0.0,
      "cpu_time": 0.0,
      "status": 1,
      "starttime": 1758767662.804935,
      "endtime": 1758767662.804935,
      "additional_info": {}
    },
    {
      "config_id": 10,
      "instance": null,
      "seed": 42,
      "budget": null,
      "cost": 0.9931,
      "time": 0.0,
      "cpu_time": 0.0,
      "status": 1,
      "starttime": 1758767663.2059348,
      "endtime": 1758767663.2059348,
      "additional_info": {}
    },
    {
      "config_id": 10,
      "instance": null,
      "seed": 209652396,
      "budget": null,
      "cost": 0.9931,
      "time": 0.0,
      "cpu_time": 0.0,
      "status": 1,
      "starttime": 1758767663.2129354,
      "endtime": 1758767663.2129354,
      "additional_info": {}
    },
    {
      "config_id": 10,
      "instance": null,
      "seed": 398764591,
      "budget": null,
      "cost": 0.9931,
      "time": 0.0,
      "cpu_time": 0.0,
      "status": 1,
      "starttime": 1758767663.2179348,
      "endtime": 1758767663.2179348,
      "additional_info": {}
    },
    {
      "config_id": 11,
      "instance": null,
      "seed": 42,
      "budget": null,
      "cost": 0.9927,
      "time": 0.0,
      "cpu_time": 0.0,
      "status": 1,
      "starttime": 1758767663.2239347,
      "endtime": 1758767663.2259347,
      "additional_info": {}
    },
    {
      "config_id": 11,
      "instance": null,
      "seed": 209652396,
      "budget": null,
      "cost": 0.9927,
      "time": 0.0,
      "cpu_time": 0.0,
      "status": 1,
      "starttime": 1758767663.2309349,
      "endtime": 1758767663.2309349,
      "additional_info": {}
    },
    {
      "config_id": 11,
      "instance": null,
      "seed": 398764591,
      "budget": null,
      "cost": 0.9927,
      "time": 0.0,
      "cpu_time": 0.0,
      "status": 1,
      "starttime": 1758767663.2359347,
      "endtime": 1758767663.236935,
      "additional_info": {}
    },
    {
      "config_id": 12,
      "instance": null,
      "seed": 42,
      "budget": null,
      "cost": 0.9881,
      "time": 0.0,
      "cpu_time": 0.0,
      "status": 1,
      "starttime": 1758767663.2509348,
      "endtime": 1758767663.2529347,
      "additional_info": {}
    },
    {
      "config_id": 12,
      "instance": null,
      "seed": 209652396,
      "budget": null,
      "cost": 0.9881,
      "time": 0.0,
      "cpu_time": 0.0,
      "status": 1,
      "starttime": 1758767663.2629347,
      "endtime": 1758767663.264935,
      "additional_info": {}
    },
    {
      "config_id": 12,
      "instance": null,
      "seed": 398764591,
      "budget": null,
      "cost": 0.9881,
      "time": 0.0,
      "cpu_time": 0.0,
      "status": 1,
      "starttime": 1758767663.269935,
      "endtime": 1758767663.2709348,
      "additional_info": {}
    },
    {
      "config_id": 13,
      "instance": null,
      "seed": 42,
      "budget": null,
      "cost": 0.9931,
      "time": 0.0,
      "cpu_time": 0.0,
      "status": 1,
      "starttime": 1758767663.2789352,
      "endtime": 1758767663.2799356,
      "additional_info": {}
    },
    {
      "config_id": 13,
      "instance": null,
      "seed": 209652396,
      "budget": null,
      "cost": 0.9931,
      "time": 0.0,
      "cpu_time": 0.0,
      "status": 1,
      "starttime": 1758767663.284935,
      "endtime": 1758767663.285935,
      "additional_info": {}
    },
    {
      "config_id": 13,
      "instance": null,
      "seed": 398764591,
      "budget": null,
      "cost": 0.9931,
      "time": 0.0,
      "cpu_time": 0.0,
      "status": 1,
      "starttime": 1758767663.292935,
      "endtime": 1758767663.292935,
      "additional_info": {}
    },
    {
      "config_id": 14,
      "instance": null,
      "seed": 42,
      "budget": null,
      "cost": 0.9889,
      "time": 0.0,
      "cpu_time": 0.0,
      "status": 1,
      "starttime": 1758767663.300935,
      "endtime": 1758767663.302935,
      "additional_info": {}
    },
    {
      "config_id": 14,
      "instance": null,
      "seed": 209652396,
      "budget": null,
      "cost": 0.9889,
      "time": 0.0,
      "cpu_time": 0.0,
      "status": 1,
      "starttime": 1758767663.3069348,
      "endtime": 1758767663.3079352,
      "additional_info": {}
    },
    {
      "config_id": 14,
      "instance": null,
      "seed": 398764591,
      "budget": null,
      "cost": 0.9889,
      "time": 0.0,
      "cpu_time": 0.0,
      "status": 1,
      "starttime": 1758767663.3229349,
      "endtime": 1758767663.3229349,
      "additional_info": {}
    },
    {
      "config_id": 15,
      "instance": null,
      "seed": 42,
      "budget": null,
      "cost": 0.9931,
      "time": 0.0,
      "cpu_time": 0.0,
      "status": 1,
      "starttime": 1758767663.805935,
      "endtime": 1758767663.8069348,
      "additional_info": {}
    },
    {
      "config_id": 15,
      "instance": null,
      "seed": 209652396,
      "budget": null,
      "cost": 0.9931,
      "time": 0.0,
      "cpu_time": 0.0,
      "status": 1,
      "starttime": 1758767663.811935,
      "endtime": 1758767663.811935,
      "additional_info": {}
    },
    {
      "config_id": 15,
      "instance": null,
      "seed": 398764591,
      "budget": null,
      "cost": 0.9931,
      "time": 0.0,
      "cpu_time": 0.0,
      "status": 1,
      "starttime": 1758767663.8179348,
      "endtime": 1758767663.8179348,
      "additional_info": {}
    },
    {
      "config_id": 16,
      "instance": null,
      "seed": 42,
      "budget": null,
      "cost": 0.9666,
      "time": 0.0,
      "cpu_time": 0.0,
      "status": 1,
      "starttime": 1758767663.823935,
      "endtime": 1758767663.823935,
      "additional_info": {}
    },
    {
      "config_id": 16,
      "instance": null,
      "seed": 209652396,
      "budget": null,
      "cost": 0.9666,
      "time": 0.0,
      "cpu_time": 0.0,
      "status": 1,
      "starttime": 1758767663.828935,
      "endtime": 1758767663.829935,
      "additional_info": {}
    },
    {
      "config_id": 16,
      "instance": null,
      "seed": 398764591,
      "budget": null,
      "cost": 0.9666,
      "time": 0.0,
      "cpu_time": 0.0,
      "status": 1,
      "starttime": 1758767663.8359349,
      "endtime": 1758767663.8369353,
      "additional_info": {}
    },
    {
      "config_id": 17,
      "instance": null,
      "seed": 42,
      "budget": null,
      "cost": 1.0,
      "time": 0.0,
      "cpu_time": 0.0,
      "status": 1,
      "starttime": 1758767663.8429348,
      "endtime": 1758767663.8429348,
      "additional_info": {}
    },
    {
      "config_id": 17,
      "instance": null,
      "seed": 209652396,
      "budget": null,
      "cost": 1.0,
      "time": 0.0,
      "cpu_time": 0.0,
      "status": 1,
      "starttime": 1758767663.847935,
      "endtime": 1758767663.8489351,
      "additional_info": {}
    },
    {
      "config_id": 17,
      "instance": null,
      "seed": 398764591,
      "budget": null,
      "cost": 1.0,
      "time": 0.0,
      "cpu_time": 0.0,
      "status": 1,
      "starttime": 1758767663.8539357,
      "endtime": 1758767663.8539357,
      "additional_info": {}
    },
    {
      "config_id": 18,
      "instance": null,
      "seed": 42,
      "budget": null,
      "cost": 0.663,
      "time": 0.0,
      "cpu_time": 0.0,
      "status": 1,
      "starttime": 1758767663.8619356,
      "endtime": 1758767663.8619356,
      "additional_info": {}
    },
    {
      "config_id": 18,
      "instance": null,
      "seed": 209652396,
      "budget": null,
      "cost": 0.663,
      "time": 0.0,
      "cpu_time": 0.0,
      "status": 1,
      "starttime": 1758767663.8679354,
      "endtime": 1758767663.8689349,
      "additional_info": {}
    },
    {
      "config_id": 18,
      "instance": null,
      "seed": 398764591,
      "budget": null,
      "cost": 0.663,
      "time": 0.0,
      "cpu_time": 0.0,
      "status": 1,
      "starttime": 1758767663.8749359,
      "endtime": 1758767663.8759363,
      "additional_info": {}
    },
    {
      "config_id": 19,
      "instance": null,
      "seed": 42,
      "budget": null,
      "cost": 0.34950000000000003,
      "time": 0.0,
      "cpu_time": 0.0,
      "status": 1,
      "starttime": 1758767663.8849368,
      "endtime": 1758767663.885937,
      "additional_info": {}
    },
    {
      "config_id": 19,
      "instance": null,
      "seed": 209652396,
      "budget": null,
      "cost": 0.34950000000000003,
      "time": 0.0,
      "cpu_time": 0.0,
      "status": 1,
      "starttime": 1758767663.8939352,
      "endtime": 1758767663.8939352,
      "additional_info": {}
    },
    {
      "config_id": 19,
      "instance": null,
      "seed": 398764591,
      "budget": null,
      "cost": 0.34950000000000003,
      "time": 0.0,
      "cpu_time": 0.0,
      "status": 1,
      "starttime": 1758767663.9049354,
      "endtime": 1758767663.9059353,
      "additional_info": {}
    },
    {
      "config_id": 20,
      "instance": null,
      "seed": 42,
      "budget": null,
      "cost": 0.9951,
      "time": 0.0,
      "cpu_time": 0.0,
      "status": 1,
      "starttime": 1758767663.9179358,
      "endtime": 1758767663.9179358,
      "additional_info": {}
    },
    {
      "config_id": 20,
      "instance": null,
      "seed": 209652396,
      "budget": null,
      "cost": 0.9951,
      "time": 0.0,
      "cpu_time": 0.0,
      "status": 1,
      "starttime": 1758767663.923935,
      "endtime": 1758767663.924935,
      "additional_info": {}
    },
    {
      "config_id": 20,
      "instance": null,
      "seed": 398764591,
      "budget": null,
      "cost": 0.9951,
      "time": 0.0,
      "cpu_time": 0.0,
      "status": 1,
      "starttime": 1758767663.9339354,
      "endtime": 1758767663.9349365,
      "additional_info": {}
    },
    {
      "config_id": 21,
      "instance": null,
      "seed": 42,
      "budget": null,
      "cost": 0.9912,
      "time": 0.0,
      "cpu_time": 0.0,
      "status": 1,
      "starttime": 1758767663.943935,
      "endtime": 1758767663.943935,
      "additional_info": {}
    },
    {
      "config_id": 21,
      "instance": null,
      "seed": 209652396,
      "budget": null,
      "cost": 0.9912,
      "time": 0.0,
      "cpu_time": 0.0,
      "status": 1,
      "starttime": 1758767663.949935,
      "endtime": 1758767663.949935,
      "additional_info": {}
    },
    {
      "config_id": 21,
      "instance": null,
      "seed": 398764591,
      "budget": null,
      "cost": 0.9912,
      "time": 0.0,
      "cpu_time": 0.0,
      "status": 1,
      "starttime": 1758767663.9559348,
      "endtime": 1758767663.9559348,
      "additional_info": {}
    },
    {
      "config_id": 22,
      "instance": null,
      "seed": 42,
      "budget": null,
      "cost": 0.09440000000000004,
      "time": 0.0,
      "cpu_time": 0.0,
      "status": 1,
      "starttime": 1758767664.3689349,
      "endtime": 1758767664.3699348,
      "additional_info": {}
    },
    {
      "config_id": 22,
      "instance": null,
      "seed": 209652396,
      "budget": null,
      "cost": 0.09440000000000004,
      "time": 0.0,
      "cpu_time": 0.0,
      "status": 1,
      "starttime": 1758767664.3759346,
      "endtime": 1758767664.3779352,
      "additional_info": {}
    },
    {
      "config_id": 22,
      "instance": null,
      "seed": 398764591,
      "budget": null,
      "cost": 0.09440000000000004,
      "time": 0.0,
      "cpu_time": 0.0,
      "status": 1,
      "starttime": 1758767664.3889346,
      "endtime": 1758767664.3889346,
      "additional_info": {}
    },
    {
      "config_id": 23,
      "instance": null,
      "seed": 42,
      "budget": null,
      "cost": 0.9948,
      "time": 0.0,
      "cpu_time": 0.0,
      "status": 1,
      "starttime": 1758767664.395935,
      "endtime": 1758767664.395935,
      "additional_info": {}
    },
    {
      "config_id": 23,
      "instance": null,
      "seed": 209652396,
      "budget": null,
      "cost": 0.9948,
      "time": 0.0,
      "cpu_time": 0.0,
      "status": 1,
      "starttime": 1758767664.404935,
      "endtime": 1758767664.4059348,
      "additional_info": {}
    },
    {
      "config_id": 23,
      "instance": null,
      "seed": 398764591,
      "budget": null,
      "cost": 0.9948,
      "time": 0.0,
      "cpu_time": 0.0,
      "status": 1,
      "starttime": 1758767664.411935,
      "endtime": 1758767664.411935,
      "additional_info": {}
    },
    {
      "config_id": 24,
      "instance": null,
      "seed": 42,
      "budget": null,
      "cost": 0.5863,
      "time": 0.0,
      "cpu_time": 0.0,
      "status": 1,
      "starttime": 1758767664.4229352,
      "endtime": 1758767664.4239354,
      "additional_info": {}
    },
    {
      "config_id": 24,
      "instance": null,
      "seed": 209652396,
      "budget": null,
      "cost": 0.5863,
      "time": 0.0,
      "cpu_time": 0.0,
      "status": 1,
      "starttime": 1758767664.4299352,
      "endtime": 1758767664.4309347,
      "additional_info": {}
    },
    {
      "config_id": 24,
      "instance": null,
      "seed": 398764591,
      "budget": null,
      "cost": 0.5863,
      "time": 0.0,
      "cpu_time": 0.0,
      "status": 1,
      "starttime": 1758767664.436935,
      "endtime": 1758767664.4379349,
      "additional_info": {}
    },
    {
      "config_id": 25,
      "instance": null,
      "seed": 42,
      "budget": null,
      "cost": 0.9097999999999999,
      "time": 0.0,
      "cpu_time": 0.0,
      "status": 1,
      "starttime": 1758767664.443935,
      "endtime": 1758767664.443935,
      "additional_info": {}
    },
    {
      "config_id": 25,
      "instance": null,
      "seed": 209652396,
      "budget": null,
      "cost": 0.9097999999999999,
      "time": 0.0,
      "cpu_time": 0.0,
      "status": 1,
      "starttime": 1758767664.450935,
      "endtime": 1758767664.450935,
      "additional_info": {}
    },
    {
      "config_id": 25,
      "instance": null,
      "seed": 398764591,
      "budget": null,
      "cost": 0.9097999999999999,
      "time": 0.0,
      "cpu_time": 0.0,
      "status": 1,
      "starttime": 1758767664.458935,
      "endtime": 1758767664.458935,
      "additional_info": {}
    },
    {
      "config_id": 26,
      "instance": null,
      "seed": 42,
      "budget": null,
      "cost": 0.5903,
      "time": 0.0,
      "cpu_time": 0.0,
      "status": 1,
      "starttime": 1758767664.8509352,
      "endtime": 1758767664.851935,
      "additional_info": {}
    },
    {
      "config_id": 26,
      "instance": null,
      "seed": 209652396,
      "budget": null,
      "cost": 0.5903,
      "time": 0.0,
      "cpu_time": 0.0,
      "status": 1,
      "starttime": 1758767664.858935,
      "endtime": 1758767664.858935,
      "additional_info": {}
    },
    {
      "config_id": 26,
      "instance": null,
      "seed": 398764591,
      "budget": null,
      "cost": 0.5903,
      "time": 0.0,
      "cpu_time": 0.0,
      "status": 1,
      "starttime": 1758767664.865935,
      "endtime": 1758767664.865935,
      "additional_info": {}
    },
    {
      "config_id": 27,
      "instance": null,
      "seed": 42,
      "budget": null,
      "cost": 0.9787,
      "time": 0.0,
      "cpu_time": 0.0,
      "status": 1,
      "starttime": 1758767664.8739347,
      "endtime": 1758767664.8739347,
      "additional_info": {}
    },
    {
      "config_id": 27,
      "instance": null,
      "seed": 209652396,
      "budget": null,
      "cost": 0.9787,
      "time": 0.0,
      "cpu_time": 0.0,
      "status": 1,
      "starttime": 1758767664.8839355,
      "endtime": 1758767664.8849354,
      "additional_info": {}
    },
    {
      "config_id": 27,
      "instance": null,
      "seed": 398764591,
      "budget": null,
      "cost": 0.9787,
      "time": 0.0,
      "cpu_time": 0.0,
      "status": 1,
      "starttime": 1758767664.8939352,
      "endtime": 1758767664.894936,
      "additional_info": {}
    },
    {
      "config_id": 28,
      "instance": null,
      "seed": 42,
      "budget": null,
      "cost": 0.5967,
      "time": 0.0,
      "cpu_time": 0.0,
      "status": 1,
      "starttime": 1758767664.9049354,
      "endtime": 1758767664.9049354,
      "additional_info": {}
    },
    {
      "config_id": 28,
      "instance": null,
      "seed": 209652396,
      "budget": null,
      "cost": 0.5967,
      "time": 0.0,
      "cpu_time": 0.0,
      "status": 1,
      "starttime": 1758767664.911935,
      "endtime": 1758767664.912935,
      "additional_info": {}
    },
    {
      "config_id": 28,
      "instance": null,
      "seed": 398764591,
      "budget": null,
      "cost": 0.5967,
      "time": 0.0,
      "cpu_time": 0.0,
      "status": 1,
      "starttime": 1758767664.9219353,
      "endtime": 1758767664.9229352,
      "additional_info": {}
    },
    {
      "config_id": 29,
      "instance": null,
      "seed": 42,
      "budget": null,
      "cost": 0.7086,
      "time": 0.0,
      "cpu_time": 0.0,
      "status": 1,
      "starttime": 1758767664.934935,
      "endtime": 1758767664.934935,
      "additional_info": {}
    },
    {
      "config_id": 29,
      "instance": null,
      "seed": 209652396,
      "budget": null,
      "cost": 0.7086,
      "time": 0.0,
      "cpu_time": 0.0,
      "status": 1,
      "starttime": 1758767664.9449348,
      "endtime": 1758767664.945935,
      "additional_info": {}
    },
    {
      "config_id": 29,
      "instance": null,
      "seed": 398764591,
      "budget": null,
      "cost": 0.7086,
      "time": 0.0,
      "cpu_time": 0.0,
      "status": 1,
      "starttime": 1758767664.9539351,
      "endtime": 1758767664.9539351,
      "additional_info": {}
    },
    {
      "config_id": 30,
      "instance": null,
      "seed": 42,
      "budget": null,
      "cost": 0.9969,
      "time": 0.0,
      "cpu_time": 0.0,
      "status": 1,
      "starttime": 1758767664.962935,
      "endtime": 1758767664.962935,
      "additional_info": {}
    },
    {
      "config_id": 30,
      "instance": null,
      "seed": 209652396,
      "budget": null,
      "cost": 0.9969,
      "time": 0.0,
      "cpu_time": 0.0,
      "status": 1,
      "starttime": 1758767664.9719353,
      "endtime": 1758767664.9729362,
      "additional_info": {}
    },
    {
      "config_id": 30,
      "instance": null,
      "seed": 398764591,
      "budget": null,
      "cost": 0.9969,
      "time": 0.0,
      "cpu_time": 0.0,
      "status": 1,
      "starttime": 1758767664.9799347,
      "endtime": 1758767664.9799347,
      "additional_info": {}
    },
    {
      "config_id": 31,
      "instance": null,
      "seed": 42,
      "budget": null,
      "cost": 0.9289000000000001,
      "time": 0.0,
      "cpu_time": 0.0,
      "status": 1,
      "starttime": 1758767664.987935,
      "endtime": 1758767664.988935,
      "additional_info": {}
    },
    {
      "config_id": 31,
      "instance": null,
      "seed": 209652396,
      "budget": null,
      "cost": 0.9289000000000001,
      "time": 0.0,
      "cpu_time": 0.0,
      "status": 1,
      "starttime": 1758767664.9959347,
      "endtime": 1758767664.9959347,
      "additional_info": {}
    },
    {
      "config_id": 31,
      "instance": null,
      "seed": 398764591,
      "budget": null,
      "cost": 0.9289000000000001,
      "time": 0.0,
      "cpu_time": 0.0,
      "status": 1,
      "starttime": 1758767665.002935,
      "endtime": 1758767665.0039346,
      "additional_info": {}
    },
    {
      "config_id": 32,
      "instance": null,
      "seed": 42,
      "budget": null,
      "cost": 0.808,
      "time": 0.0,
      "cpu_time": 0.0,
      "status": 1,
      "starttime": 1758767665.0129356,
      "endtime": 1758767665.013935,
      "additional_info": {}
    },
    {
      "config_id": 32,
      "instance": null,
      "seed": 209652396,
      "budget": null,
      "cost": 0.808,
      "time": 0.0,
      "cpu_time": 0.0,
      "status": 1,
      "starttime": 1758767665.0209348,
      "endtime": 1758767665.0219347,
      "additional_info": {}
    },
    {
      "config_id": 32,
      "instance": null,
      "seed": 398764591,
      "budget": null,
      "cost": 0.808,
      "time": 0.0,
      "cpu_time": 0.0,
      "status": 1,
      "starttime": 1758767665.029935,
      "endtime": 1758767665.029935,
      "additional_info": {}
    },
    {
      "config_id": 33,
      "instance": null,
      "seed": 42,
      "budget": null,
      "cost": 0.9809,
      "time": 0.0,
      "cpu_time": 0.0,
      "status": 1,
      "starttime": 1758767665.053935,
      "endtime": 1758767665.0549357,
      "additional_info": {}
    }
  ],
  "configs": {
    "1": {
      "x": 97
    },
    "2": {
      "x": 4
    },
    "3": {
      "x": 37
    },
    "4": {
      "x": 41
    },
    "5": {
      "x": 6
    },
    "6": {
      "x": 9
    },
    "7": {
      "x": 20
    },
    "8": {
      "x": 43
    },
    "9": {
      "x": 28
    },
    "10": {
      "x": 5
    },
    "11": {
      "x": 92
    },
    "12": {
      "x": 35
    },
    "13": {
      "x": 1
    },
    "14": {
      "x": 3
    },
    "15": {
      "x": 50
    },
    "16": {
      "x": 49
    },
    "17": {
      "x": 60
    },
    "18": {
      "x": 13
    },
    "19": {
      "x": 42
    },
    "20": {
      "x": 2
    },
    "21": {
      "x": 15
    },
    "22": {
      "x": 44
    },
    "23": {
      "x": 11
    },
    "24": {
      "x": 58
    },
    "25": {
      "x": 95
    },
    "26": {
      "x": 45
    },
    "27": {
      "x": 27
    },
    "28": {
      "x": 46
    },
    "29": {
      "x": 88
    },
    "30": {
      "x": 10
    },
    "31": {
      "x": 12
    },
    "32": {
      "x": 24
    },
    "33": {
      "x": 40
    }
  },
  "config_origins": {
    "1": "Initial design",
    "2": "Acquisition Function Maximizer: Local Search",
    "3": "Acquisition Function Maximizer: Local Search",
    "4": "Acquisition Function Maximizer: Local Search",
    "5": "Acquisition Function Maximizer: Local Search",
    "6": "Acquisition Function Maximizer: Local Search",
    "7": "Acquisition Function Maximizer: Local Search",
    "8": "Acquisition Function Maximizer: Local Search",
    "9": "Acquisition Function Maximizer: Local Search",
    "10": "Acquisition Function Maximizer: Local Search",
    "11": "Random Search",
    "12": "Random Search",
    "13": "Acquisition Function Maximizer: Local Search",
    "14": "Acquisition Function Maximizer: Local Search",
    "15": "Acquisition Function Maximizer: Local Search",
    "16": "Acquisition Function Maximizer: Local Search",
    "17": "Random Search",
    "18": "Random Search",
    "19": "Acquisition Function Maximizer: Local Search",
    "20": "Acquisition Function Maximizer: Local Search",
    "21": "Random Search",
    "22": "Acquisition Function Maximizer: Local Search",
    "23": "Acquisition Function Maximizer: Local Search",
    "24": "Random Search",
    "25": "Acquisition Function Maximizer: Local Search",
    "26": "Acquisition Function Maximizer: Local Search",
    "27": "Random Search",
    "28": "Acquisition Function Maximizer: Local Search",
    "29": "Random Search",
    "30": "Random Search",
    "31": "Acquisition Function Maximizer: Local Search",
    "32": "Random Search",
    "33": "Random Search"
  }
}